{
  "annotations": {
    "list": [
      {
        "builtIn": 1,
        "datasource": {
          "uid": "-- Grafana --"
        },
        "enable": true,
        "hide": true,
        "iconColor": "rgba(0, 211, 255, 1)",
        "name": "Annotations & Alerts",
        "target": {
          "limit": 100,
          "matchAny": false,
          "tags": [],
          "type": "dashboard"
        },
        "type": "dashboard"
      }
    ]
  },
  "editable": true,
  "fiscalYearStartMonth": 0,
  "graphTooltip": 0,
  "id": 1,
  "links": [],
  "panels": [
    {
      "datasource": "Docker InfluxDB",
      "fieldConfig": {
        "defaults": {
          "color": {
            "mode": "thresholds"
          },
          "custom": {
            "align": "auto",
            "cellOptions": {
              "mode": "basic",
              "type": "color-background"
            },
            "filterable": false,
            "footer": {
              "reducers": []
            },
            "inspect": false
          },
          "mappings": [],
          "thresholds": {
            "mode": "absolute",
            "steps": [
              {
                "color": "green",
                "value": 0
              },
              {
                "color": "red",
                "value": 80
              }
            ]
          }
        },
        "overrides": []
      },
      "gridPos": {
        "h": 3,
        "w": 6,
        "x": 0,
        "y": 0
      },
      "id": 19,
      "options": {
        "cellHeight": "sm",
        "frameIndex": 1,
        "showHeader": false
      },
      "pluginVersion": "12.3.0-18783997389",
      "targets": [
        {
          "alias": "Type",
          "datasource": "Docker InfluxDB",
          "groupBy": [],
          "measurement": "nokia_port_string",
          "orderByTime": "ASC",
          "policy": "default",
          "query": "SELECT last(\"transceiver_type\") FROM \"nokia_port_string\" WHERE (\"source\"::tag =~ /^$HostName$/) AND $timeFilter",
          "rawQuery": false,
          "refId": "A",
          "resultFormat": "logs",
          "select": [
            [
              {
                "params": [
                  "transceiver_type"
                ],
                "type": "field"
              },
              {
                "params": [],
                "type": "last"
              }
            ]
          ],
          "tags": [
            {
              "key": "source::tag",
              "operator": "=~",
              "value": "/^$HostName$/"
            }
          ]
        }
      ],
      "title": "Transceiver Type",
      "type": "table"
    },
    {
      "datasource": "Docker InfluxDB",
      "fieldConfig": {
        "defaults": {
          "color": {
            "mode": "thresholds"
          },
          "custom": {
            "align": "auto",
            "cellOptions": {
              "mode": "basic",
              "type": "color-background"
            },
            "filterable": false,
            "footer": {
              "reducers": []
            },
            "inspect": false
          },
          "mappings": [],
          "thresholds": {
            "mode": "absolute",
            "steps": [
              {
                "color": "green",
                "value": 0
              },
              {
                "color": "red",
                "value": 80
              }
            ]
          }
        },
        "overrides": []
      },
      "gridPos": {
        "h": 3,
        "w": 6,
        "x": 6,
        "y": 0
      },
      "id": 26,
      "options": {
        "cellHeight": "sm",
        "frameIndex": 1,
        "showHeader": false
      },
      "pluginVersion": "12.3.0-18783997389",
      "targets": [
        {
          "alias": "Part Number",
          "datasource": "Docker InfluxDB",
          "groupBy": [],
          "measurement": "nokia_port_string",
          "orderByTime": "ASC",
          "policy": "default",
          "refId": "A",
          "resultFormat": "logs",
          "select": [
            [
              {
                "params": [
                  "transceiver_vendor_part_number"
                ],
                "type": "field"
              },
              {
                "params": [],
                "type": "last"
              }
            ]
          ],
          "tags": [
            {
              "key": "source",
              "operator": "=~",
              "value": "/^$HostName$/"
            }
          ]
        }
      ],
      "title": "Transceiver Part Number",
      "type": "table"
    },
    {
      "datasource": "Docker InfluxDB",
      "description": "",
      "fieldConfig": {
        "defaults": {
          "color": {
            "mode": "palette-classic"
          },
          "custom": {
            "axisBorderShow": false,
            "axisCenteredZero": false,
            "axisColorMode": "text",
            "axisLabel": "",
            "axisPlacement": "auto",
            "barAlignment": 0,
            "barWidthFactor": 0.6,
            "drawStyle": "line",
            "fillOpacity": 0,
            "gradientMode": "none",
            "hideFrom": {
              "legend": false,
              "tooltip": false,
              "viz": false
            },
            "insertNulls": false,
            "lineInterpolation": "linear",
            "lineWidth": 1,
            "pointSize": 5,
            "scaleDistribution": {
              "type": "linear"
            },
            "showPoints": "auto",
            "showValues": false,
            "spanNulls": false,
            "stacking": {
              "group": "A",
              "mode": "none"
            },
            "thresholdsStyle": {
              "mode": "off"
            }
          },
          "mappings": [],
          "thresholds": {
            "mode": "absolute",
            "steps": [
              {
                "color": "green",
                "value": 0
              },
              {
                "color": "red",
                "value": 80
              }
            ]
          },
          "unit": "binbps"
        },
        "overrides": []
      },
      "gridPos": {
        "h": 6,
        "w": 8,
        "x": 12,
        "y": 0
      },
      "id": 17,
      "options": {
        "legend": {
          "calcs": [
            "lastNotNull"
          ],
          "displayMode": "list",
          "placement": "bottom",
          "showLegend": true
        },
        "tooltip": {
          "hideZeros": false,
          "mode": "single",
          "sort": "none"
        }
      },
      "pluginVersion": "12.3.0-18783997389",
      "targets": [
        {
          "alias": "Incoming Traffic",
          "datasource": "Docker InfluxDB",
          "groupBy": [
            {
              "params": [
                "$__interval"
              ],
              "type": "time"
            },
            {
              "params": [
                "null"
              ],
              "type": "fill"
            }
          ],
          "hide": false,
          "measurement": "nokia_port_ethernet_statistics",
          "orderByTime": "ASC",
          "policy": "default",
          "query": "SELECT 8 * derivative(mean(\"in_octets\"),1s) FROM \"nokia_port_ethernet_statistics\" WHERE (\"source\" =~ /^$HostName$/ AND \"port_id\" = '$EthPortNumber') AND $timeFilter GROUP BY time($__interval) fill(null)",
          "rawQuery": true,
          "refId": "C",
          "resultFormat": "time_series",
          "select": [
            [
              {
                "params": [
                  "in_octets"
                ],
                "type": "field"
              },
              {
                "params": [],
                "type": "mean"
              }
            ]
          ],
          "tags": [
            {
              "key": "source",
              "operator": "=",
              "value": "172.30.150.150"
            },
            {
              "condition": "AND",
              "key": "port_id",
              "operator": "=",
              "value": "1/1/c34/1"
            }
          ]
        },
        {
          "alias": "Outgoing Traffic",
          "datasource": "Docker InfluxDB",
          "hide": false,
          "query": "SELECT 8 * derivative(mean(\"out_octets\"),1s) FROM \"nokia_port_ethernet_statistics\" WHERE (\"source\" =~ /^$HostName$/ AND \"port_id\" = '$EthPortNumber') AND $timeFilter GROUP BY time($__interval) fill(null)",
          "rawQuery": true,
          "refId": "B",
          "resultFormat": "time_series"
        }
      ],
      "title": "Traffic Volume",
      "type": "timeseries"
    },
    {
      "datasource": "Docker InfluxDB",
      "fieldConfig": {
        "defaults": {
          "color": {
            "mode": "thresholds"
          },
          "custom": {
            "align": "auto",
            "cellOptions": {
              "mode": "basic",
              "type": "color-background"
            },
            "filterable": false,
            "footer": {
              "reducers": []
            },
            "inspect": false
          },
          "mappings": [],
          "thresholds": {
            "mode": "absolute",
            "steps": [
              {
                "color": "green",
                "value": 0
              },
              {
                "color": "green",
                "value": 80
              },
              {
                "color": "red",
                "value": 500
              }
            ]
          },
          "unit": "Gbits"
        },
        "overrides": []
      },
      "gridPos": {
        "h": 3,
        "w": 6,
        "x": 0,
        "y": 3
      },
      "id": 28,
      "options": {
        "cellHeight": "sm",
        "frameIndex": 1,
        "showHeader": false
      },
      "pluginVersion": "12.3.0-18783997389",
      "targets": [
        {
          "alias": "Bandwidth",
          "datasource": "Docker InfluxDB",
          "groupBy": [],
          "measurement": "nokia_port_ethernet",
          "orderByTime": "ASC",
          "policy": "default",
          "refId": "A",
          "resultFormat": "logs",
          "select": [
            [
              {
                "params": [
                  "oper_speed"
                ],
                "type": "field"
              },
              {
                "params": [],
                "type": "last"
              },
              {
                "params": [
                  " / 1000"
                ],
                "type": "math"
              }
            ]
          ],
          "tags": [
            {
              "key": "source",
              "operator": "=~",
              "value": "/^$HostName$/"
            }
          ]
        }
      ],
      "title": "Transceiver Bandwidth",
      "type": "table"
    },
    {
      "datasource": "Docker InfluxDB",
      "fieldConfig": {
        "defaults": {
          "color": {
            "mode": "thresholds"
          },
          "custom": {
            "align": "auto",
            "cellOptions": {
              "mode": "basic",
              "type": "color-background"
            },
            "filterable": false,
            "footer": {
              "reducers": []
            },
            "inspect": false
          },
          "mappings": [],
          "thresholds": {
            "mode": "absolute",
            "steps": [
              {
                "color": "green",
                "value": 0
              },
              {
                "color": "red",
                "value": 80
              }
            ]
          }
        },
        "overrides": []
      },
      "gridPos": {
        "h": 3,
        "w": 6,
        "x": 6,
        "y": 3
      },
      "id": 27,
      "options": {
        "cellHeight": "sm",
        "frameIndex": 1,
        "showHeader": false
      },
      "pluginVersion": "12.3.0-18783997389",
      "targets": [
        {
          "alias": "Serial Number",
          "datasource": "Docker InfluxDB",
          "groupBy": [],
          "measurement": "nokia_port_string",
          "orderByTime": "ASC",
          "policy": "default",
          "refId": "A",
          "resultFormat": "logs",
          "select": [
            [
              {
                "params": [
                  "transceiver_vendor_serial_number"
                ],
                "type": "field"
              },
              {
                "params": [],
                "type": "last"
              }
            ]
          ],
          "tags": [
            {
              "key": "source",
              "operator": "=~",
              "value": "/^$HostName$/"
            }
          ]
        }
      ],
      "title": "Transceiver Serial Number",
      "type": "table"
    },
    {
      "datasource": "Docker InfluxDB",
      "fieldConfig": {
        "defaults": {
          "color": {
            "mode": "palette-classic"
          },
          "mappings": [],
          "max": 0,
          "min": -20,
          "thresholds": {
            "mode": "absolute",
            "steps": [
              {
                "color": "green",
                "value": 0
              },
              {
                "color": "red",
                "value": 80
              }
            ]
          },
          "unit": "dBm"
        },
        "overrides": []
      },
      "gridPos": {
        "h": 4,
        "w": 4,
        "x": 0,
        "y": 6
      },
      "id": 4,
      "options": {
        "colorMode": "value",
        "graphMode": "area",
        "justifyMode": "auto",
        "orientation": "auto",
        "percentChangeColorMode": "standard",
        "reduceOptions": {
          "calcs": [
            "lastNotNull"
          ],
          "fields": "",
          "values": false
        },
        "showPercentChange": false,
        "text": {},
        "textMode": "auto",
        "wideLayout": true
      },
      "pluginVersion": "12.3.0-18783997389",
      "targets": [
        {
          "alias": "Rx Power",
          "datasource": "Docker InfluxDB",
          "groupBy": [
            {
              "params": [
                "$__interval"
              ],
              "type": "time"
            },
            {
              "params": [
                "source"
              ],
              "type": "tag"
            },
            {
              "params": [
                "name"
              ],
              "type": "tag"
            },
            {
              "params": [
                "null"
              ],
              "type": "fill"
            }
          ],
          "measurement": "nokia_port_dwdm",
          "orderByTime": "ASC",
          "policy": "default",
          "query": "SELECT last(\"coherent_statistics_received_power_current\")  / 100 FROM \"nokia_port_dwdm\" WHERE (\"port_id\"::tag =~ /^$PortNumber$/) AND $timeFilter GROUP BY time($__interval), \"source\", \"name\" fill(null)",
          "rawQuery": false,
          "refId": "A",
          "resultFormat": "time_series",
          "select": [
            [
              {
                "params": [
                  "coherent_statistics_received_power_current"
                ],
                "type": "field"
              },
              {
                "params": [],
                "type": "last"
              },
              {
                "params": [
                  " / 100"
                ],
                "type": "math"
              }
            ]
          ],
          "tags": [
            {
              "key": "port_id::tag",
              "operator": "=",
              "value": "/^$PortNumber$/"
            }
          ]
        },
        {
          "alias": "Tx Power",
          "datasource": "Docker InfluxDB",
          "groupBy": [
            {
              "params": [
                "$__interval"
              ],
              "type": "time"
            },
            {
              "params": [
                "source"
              ],
              "type": "tag"
            },
            {
              "params": [
                "name"
              ],
              "type": "tag"
            },
            {
              "params": [
                "null"
              ],
              "type": "fill"
            }
          ],
          "hide": false,
          "measurement": "nokia_port_dwdm",
          "orderByTime": "ASC",
          "policy": "default",
          "refId": "B",
          "resultFormat": "time_series",
          "select": [
            [
              {
                "params": [
                  "coherent_statistics_transmitted_power_current"
                ],
                "type": "field"
              },
              {
                "params": [],
                "type": "mean"
              },
              {
                "params": [
                  " / 100"
                ],
                "type": "math"
              }
            ]
          ],
          "tags": [
            {
              "key": "source",
              "operator": "=~",
              "value": "/^$HostName$/"
            },
            {
              "condition": "AND",
              "key": "port_id",
              "operator": "=",
              "value": "/^$PortNumber$/"
            }
          ]
        }
      ],
      "title": "Optical Power Levels  in dBm ",
      "type": "stat"
    },
    {
      "datasource": "Docker InfluxDB",
      "description": "",
      "fieldConfig": {
        "defaults": {
          "color": {
            "mode": "thresholds"
          },
          "decimals": 1,
          "mappings": [],
          "thresholds": {
            "mode": "absolute",
            "steps": [
              {
                "color": "green",
                "value": 0
              },
              {
                "color": "#EAB839",
                "value": 100
              }
            ]
          },
          "unit": "THz"
        },
        "overrides": [
          {
            "matcher": {
              "id": "byName",
              "options": "Tx Target Power"
            },
            "properties": [
              {
                "id": "unit",
                "value": "dBm"
              },
              {
                "id": "min",
                "value": -20
              },
              {
                "id": "max",
                "value": 0
              }
            ]
          }
        ]
      },
      "gridPos": {
        "h": 4,
        "w": 4,
        "x": 4,
        "y": 6
      },
      "id": 6,
      "options": {
        "colorMode": "value",
        "graphMode": "none",
        "justifyMode": "auto",
        "orientation": "vertical",
        "percentChangeColorMode": "standard",
        "reduceOptions": {
          "calcs": [
            "lastNotNull"
          ],
          "fields": "",
          "values": false
        },
        "showPercentChange": false,
        "text": {},
        "textMode": "auto",
        "wideLayout": true
      },
      "pluginVersion": "12.3.0-18783997389",
      "targets": [
        {
          "alias": "Tx Target Power",
          "datasource": "Docker InfluxDB",
          "groupBy": [
            {
              "params": [
                "$__interval"
              ],
              "type": "time"
            },
            {
              "params": [
                "name"
              ],
              "type": "tag"
            },
            {
              "params": [
                "source"
              ],
              "type": "tag"
            },
            {
              "params": [
                "null"
              ],
              "type": "fill"
            }
          ],
          "measurement": "nokia_port_configure",
          "orderByTime": "ASC",
          "policy": "default",
          "refId": "A",
          "resultFormat": "time_series",
          "select": [
            [
              {
                "params": [
                  "dwdm_coherent_target_power"
                ],
                "type": "field"
              },
              {
                "params": [],
                "type": "mean"
              }
            ]
          ],
          "tags": [
            {
              "key": "source::tag",
              "operator": "=~",
              "value": "/^$HostName$/"
            },
            {
              "condition": "AND",
              "key": "port_id::tag",
              "operator": "=",
              "value": "/^$PortNumber$/"
            }
          ]
        },
        {
          "alias": "ITU Channel",
          "datasource": "Docker InfluxDB",
          "groupBy": [
            {
              "params": [
                "$__interval"
              ],
              "type": "time"
            },
            {
              "params": [
                "source"
              ],
              "type": "tag"
            },
            {
              "params": [
                "name"
              ],
              "type": "tag"
            },
            {
              "params": [
                "null"
              ],
              "type": "fill"
            }
          ],
          "hide": false,
          "measurement": "nokia_port_configure",
          "orderByTime": "ASC",
          "policy": "default",
          "refId": "B",
          "resultFormat": "time_series",
          "select": [
            [
              {
                "params": [
                  "dwdm_frequency"
                ],
                "type": "field"
              },
              {
                "params": [],
                "type": "mean"
              },
              {
                "params": [
                  " / 1000000"
                ],
                "type": "math"
              }
            ]
          ],
          "tags": [
            {
              "key": "source",
              "operator": "=~",
              "value": "/^$HostName$/"
            },
            {
              "condition": "AND",
              "key": "port_id",
              "operator": "=",
              "value": "/^$PortNumber$/"
            }
          ]
        }
      ],
      "title": "Configured Values",
      "type": "stat"
    },
    {
      "datasource": "Docker InfluxDB",
      "description": "",
      "fieldConfig": {
        "defaults": {
          "color": {
            "mode": "palette-classic"
          },
          "custom": {
            "axisBorderShow": false,
            "axisCenteredZero": false,
            "axisColorMode": "text",
            "axisLabel": "dBm",
            "axisPlacement": "auto",
            "barAlignment": 0,
            "barWidthFactor": 0.6,
            "drawStyle": "line",
            "fillOpacity": 0,
            "gradientMode": "none",
            "hideFrom": {
              "legend": false,
              "tooltip": false,
              "viz": false
            },
            "insertNulls": false,
            "lineInterpolation": "linear",
            "lineWidth": 1,
            "pointSize": 5,
            "scaleDistribution": {
              "type": "linear"
            },
            "showPoints": "auto",
            "showValues": false,
            "spanNulls": true,
            "stacking": {
              "group": "A",
              "mode": "none"
            },
            "thresholdsStyle": {
              "mode": "off"
            }
          },
          "mappings": [],
          "thresholds": {
            "mode": "absolute",
            "steps": [
              {
                "color": "green",
                "value": 0
              },
              {
                "color": "red",
                "value": 80
              }
            ]
          }
        },
        "overrides": []
      },
      "gridPos": {
        "h": 5,
        "w": 6,
        "x": 8,
        "y": 6
      },
      "id": 2,
      "options": {
        "legend": {
          "calcs": [
            "lastNotNull"
          ],
          "displayMode": "list",
          "placement": "bottom",
          "showLegend": true
        },
        "tooltip": {
          "hideZeros": false,
          "mode": "single",
          "sort": "none"
        }
      },
      "pluginVersion": "12.3.0-18783997389",
      "targets": [
        {
          "alias": "Rx Power",
          "datasource": "Docker InfluxDB",
          "groupBy": [
            {
              "params": [
                "$__interval"
              ],
              "type": "time"
            },
            {
              "params": [
                "source"
              ],
              "type": "tag"
            },
            {
              "params": [
                "name"
              ],
              "type": "tag"
            },
            {
              "params": [
                "null"
              ],
              "type": "fill"
            }
          ],
          "measurement": "nokia_port_dwdm",
          "orderByTime": "ASC",
          "policy": "default",
          "refId": "A",
          "resultFormat": "time_series",
          "select": [
            [
              {
                "params": [
                  "coherent_statistics_received_power_current"
                ],
                "type": "field"
              },
              {
                "params": [],
                "type": "mean"
              },
              {
                "params": [
                  " / 100"
                ],
                "type": "math"
              }
            ]
          ],
          "tags": [
            {
              "key": "source",
              "operator": "=~",
              "value": "/^$HostName$/"
            },
            {
              "condition": "AND",
              "key": "port_id",
              "operator": "=",
              "value": "/^$PortNumber$/"
            }
          ]
        },
        {
          "alias": "Tx Power",
          "datasource": "Docker InfluxDB",
          "groupBy": [
            {
              "params": [
                "$__interval"
              ],
              "type": "time"
            },
            {
              "params": [
                "source"
              ],
              "type": "tag"
            },
            {
              "params": [
                "name"
              ],
              "type": "tag"
            },
            {
              "params": [
                "null"
              ],
              "type": "fill"
            }
          ],
          "hide": false,
          "measurement": "nokia_port_dwdm",
          "orderByTime": "ASC",
          "policy": "default",
          "refId": "B",
          "resultFormat": "time_series",
          "select": [
            [
              {
                "params": [
                  "coherent_statistics_transmitted_power_current"
                ],
                "type": "field"
              },
              {
                "params": [],
                "type": "mean"
              },
              {
                "params": [
                  " / 100"
                ],
                "type": "math"
              }
            ]
          ],
          "tags": [
            {
              "key": "source",
              "operator": "=~",
              "value": "/^$HostName$/"
            },
            {
              "condition": "AND",
              "key": "port_id",
              "operator": "=",
              "value": "/^$PortNumber$/"
            }
          ]
        }
      ],
      "title": "OpenZR+ Optical Power Levels in dBm",
      "type": "timeseries"
    },
    {
      "datasource": "Docker InfluxDB",
      "description": "BER values below 0.01 are healthy, between 0.01-0.02 indicates need for maintenance, and above 0.02 indicates likeliness of transport packet loss.",
      "fieldConfig": {
        "defaults": {
          "color": {
            "mode": "palette-classic"
          },
          "custom": {
            "axisBorderShow": false,
            "axisCenteredZero": false,
            "axisColorMode": "text",
            "axisLabel": "Bit Error Rate",
            "axisPlacement": "auto",
            "barAlignment": 0,
            "barWidthFactor": 0.6,
            "drawStyle": "line",
            "fillOpacity": 0,
            "gradientMode": "none",
            "hideFrom": {
              "legend": false,
              "tooltip": false,
              "viz": false
            },
            "insertNulls": false,
            "lineInterpolation": "linear",
            "lineWidth": 1,
            "pointSize": 5,
            "scaleDistribution": {
              "type": "linear"
            },
            "showPoints": "auto",
            "showValues": false,
            "spanNulls": true,
            "stacking": {
              "group": "A",
              "mode": "none"
            },
            "thresholdsStyle": {
              "mode": "area"
            }
          },
          "mappings": [],
          "max": 0.021,
          "min": 0,
          "thresholds": {
            "mode": "absolute",
            "steps": [
              {
                "color": "green",
                "value": 0
              },
              {
                "color": "#EAB839",
                "value": 0.01
              },
              {
                "color": "red",
                "value": 0.02
              }
            ]
          }
        },
        "overrides": []
      },
      "gridPos": {
        "h": 8,
        "w": 6,
        "x": 14,
        "y": 6
      },
      "id": 8,
      "options": {
        "legend": {
          "calcs": [
            "lastNotNull"
          ],
          "displayMode": "list",
          "placement": "bottom",
          "showLegend": true
        },
        "tooltip": {
          "hideZeros": false,
          "mode": "single",
          "sort": "none"
        }
      },
      "pluginVersion": "12.3.0-18783997389",
      "targets": [
        {
          "alias": "Pre FEC BER",
          "datasource": "Docker InfluxDB",
          "groupBy": [
            {
              "params": [
                "$__interval"
              ],
              "type": "time"
            },
            {
              "params": [
                "source"
              ],
              "type": "tag"
            },
            {
              "params": [
                "controller_name"
              ],
              "type": "tag"
            },
            {
              "params": [
                "null"
              ],
              "type": "fill"
            }
          ],
          "measurement": "nokia_port_dwdm",
          "orderByTime": "ASC",
          "policy": "default",
          "refId": "A",
          "resultFormat": "time_series",
          "select": [
            [
              {
                "params": [
                  "coherent_statistics_received_bit_error_rate_current"
                ],
                "type": "field"
              },
              {
                "params": [],
                "type": "mean"
              }
            ]
          ],
          "tags": [
            {
              "key": "source",
              "operator": "=~",
              "value": "/^$HostName$/"
            },
            {
              "condition": "AND",
              "key": "port_id",
              "operator": "=",
              "value": "/^$PortNumber$/"
            }
          ]
        },
        {
          "alias": "Coherent Frame Error",
          "datasource": "Docker InfluxDB",
          "groupBy": [
            {
              "params": [
                "$__interval"
              ],
              "type": "time"
            },
            {
              "params": [
                "source"
              ],
              "type": "tag"
            },
            {
              "params": [
                "controller_name"
              ],
              "type": "tag"
            },
            {
              "params": [
                "null"
              ],
              "type": "fill"
            }
          ],
          "hide": false,
          "measurement": "nokia_port_dwdm",
          "orderByTime": "ASC",
          "policy": "default",
          "refId": "B",
          "resultFormat": "time_series",
          "select": [
            [
              {
                "params": [
                  "coherent_statistics_received_media_frame_error_count_current"
                ],
                "type": "field"
              },
              {
                "params": [],
                "type": "mean"
              }
            ]
          ],
          "tags": [
            {
              "key": "source",
              "operator": "=~",
              "value": "/^$HostName$/"
            },
            {
              "condition": "AND",
              "key": "port_id::tag",
              "operator": "=",
              "value": "/^$PortNumber$/"
            }
          ]
        }
      ],
      "title": "Bit Error Rate",
      "type": "timeseries"
    },
    {
      "datasource": "Docker InfluxDB",
      "fieldConfig": {
        "defaults": {
          "color": {
            "mode": "thresholds"
          },
          "mappings": [],
          "thresholds": {
            "mode": "absolute",
            "steps": [
              {
                "color": "green",
                "value": 0
              },
              {
                "color": "#EAB839",
                "value": 0.01
              },
              {
                "color": "red",
                "value": 0.02
              }
            ]
          },
          "unit": "BER"
        },
        "overrides": []
      },
      "gridPos": {
        "h": 4,
        "w": 4,
        "x": 0,
        "y": 10
      },
      "id": 9,
      "options": {
        "colorMode": "value",
        "graphMode": "area",
        "justifyMode": "auto",
        "orientation": "auto",
        "percentChangeColorMode": "standard",
        "reduceOptions": {
          "calcs": [
            "lastNotNull"
          ],
          "fields": "",
          "values": false
        },
        "showPercentChange": false,
        "text": {
          "valueSize": 50
        },
        "textMode": "auto",
        "wideLayout": true
      },
      "pluginVersion": "12.3.0-18783997389",
      "targets": [
        {
          "alias": "Pre FEC BER",
          "datasource": "Docker InfluxDB",
          "groupBy": [
            {
              "params": [
                "$__interval"
              ],
              "type": "time"
            },
            {
              "params": [
                "source"
              ],
              "type": "tag"
            },
            {
              "params": [
                "controller_name"
              ],
              "type": "tag"
            },
            {
              "params": [
                "null"
              ],
              "type": "fill"
            }
          ],
          "measurement": "nokia_port_dwdm",
          "orderByTime": "ASC",
          "policy": "default",
          "refId": "A",
          "resultFormat": "time_series",
          "select": [
            [
              {
                "params": [
                  "coherent_statistics_received_bit_error_rate_current"
                ],
                "type": "field"
              },
              {
                "params": [],
                "type": "mean"
              }
            ]
          ],
          "tags": [
            {
              "key": "source",
              "operator": "=~",
              "value": "/^$HostName$/"
            },
            {
              "condition": "AND",
              "key": "port_id",
              "operator": "=",
              "value": "/^$PortNumber$/"
            }
          ]
        }
      ],
      "title": "Bit Error Rate",
      "type": "stat"
    },
    {
      "datasource": "Docker InfluxDB",
      "fieldConfig": {
        "defaults": {
          "color": {
            "mode": "palette-classic"
          },
          "mappings": [],
          "thresholds": {
            "mode": "absolute",
            "steps": [
              {
                "color": "green",
                "value": 0
              }
            ]
          },
          "unit": "celsius"
        },
        "overrides": [
          {
            "matcher": {
              "id": "byName",
              "options": "Voltage"
            },
            "properties": [
              {
                "id": "unit",
                "value": "volt"
              }
            ]
          }
        ]
      },
      "gridPos": {
        "h": 4,
        "w": 4,
        "x": 4,
        "y": 10
      },
      "id": 11,
      "options": {
        "colorMode": "value",
        "graphMode": "area",
        "justifyMode": "auto",
        "orientation": "auto",
        "percentChangeColorMode": "standard",
        "reduceOptions": {
          "calcs": [
            "lastNotNull"
          ],
          "fields": "",
          "values": false
        },
        "showPercentChange": false,
        "text": {},
        "textMode": "auto",
        "wideLayout": true
      },
      "pluginVersion": "12.3.0-18783997389",
      "targets": [
        {
          "alias": "Temperature °C",
          "datasource": "Docker InfluxDB",
          "groupBy": [
            {
              "params": [
                "$__interval"
              ],
              "type": "time"
            },
            {
              "params": [
                "source"
              ],
              "type": "tag"
            },
            {
              "params": [
                "name"
              ],
              "type": "tag"
            },
            {
              "params": [
                "null"
              ],
              "type": "fill"
            }
          ],
          "measurement": "nokia_port_transceiver",
          "orderByTime": "ASC",
          "policy": "default",
          "refId": "A",
          "resultFormat": "time_series",
          "select": [
            [
              {
                "params": [
                  "digital_diagnostic_monitoring_temperature_current"
                ],
                "type": "field"
              },
              {
                "params": [],
                "type": "mean"
              }
            ]
          ],
          "tags": [
            {
              "key": "source",
              "operator": "=~",
              "value": "/^$HostName$/"
            },
            {
              "condition": "AND",
              "key": "port_id",
              "operator": "=",
              "value": "/^$PortNumber$/"
            }
          ]
        },
        {
          "alias": "Voltage",
          "datasource": "Docker InfluxDB",
          "groupBy": [
            {
              "params": [
                "$__interval"
              ],
              "type": "time"
            },
            {
              "params": [
                "source"
              ],
              "type": "tag"
            },
            {
              "params": [
                "name"
              ],
              "type": "tag"
            },
            {
              "params": [
                "null"
              ],
              "type": "fill"
            }
          ],
          "hide": false,
          "measurement": "nokia_port_transceiver",
          "orderByTime": "ASC",
          "policy": "default",
          "refId": "B",
          "resultFormat": "time_series",
          "select": [
            [
              {
                "params": [
                  "digital_diagnostic_monitoring_supply_voltage_current"
                ],
                "type": "field"
              },
              {
                "params": [],
                "type": "mean"
              }
            ]
          ],
          "tags": [
            {
              "key": "source",
              "operator": "=~",
              "value": "/^$HostName$/"
            },
            {
              "condition": "AND",
              "key": "port_id",
              "operator": "=",
              "value": "/^$PortNumber$/"
            }
          ]
        }
      ],
      "title": "Environmentals",
      "type": "stat"
    },
    {
      "datasource": "Docker InfluxDB",
      "fieldConfig": {
        "defaults": {
          "color": {
            "mode": "palette-classic"
          },
          "custom": {
            "axisBorderShow": false,
            "axisCenteredZero": false,
            "axisColorMode": "text",
            "axisLabel": "BER",
            "axisPlacement": "auto",
            "barAlignment": 0,
            "barWidthFactor": 0.6,
            "drawStyle": "line",
            "fillOpacity": 0,
            "gradientMode": "none",
            "hideFrom": {
              "legend": false,
              "tooltip": false,
              "viz": false
            },
            "insertNulls": false,
            "lineInterpolation": "linear",
            "lineWidth": 1,
            "pointSize": 5,
            "scaleDistribution": {
              "type": "linear"
            },
            "showPoints": "auto",
            "showValues": false,
            "spanNulls": true,
            "stacking": {
              "group": "A",
              "mode": "none"
            },
            "thresholdsStyle": {
              "mode": "off"
            }
          },
          "mappings": [],
          "thresholds": {
            "mode": "absolute",
            "steps": [
              {
                "color": "green",
                "value": 0
              }
            ]
          }
        },
        "overrides": []
      },
      "gridPos": {
        "h": 5,
        "w": 6,
        "x": 8,
        "y": 11
      },
      "id": 10,
      "options": {
        "legend": {
          "calcs": [
            "lastNotNull"
          ],
          "displayMode": "list",
          "placement": "bottom",
          "showLegend": true
        },
        "tooltip": {
          "hideZeros": false,
          "mode": "single",
          "sort": "none"
        }
      },
      "pluginVersion": "12.3.0-18783997389",
      "targets": [
        {
          "alias": "°C",
          "datasource": "Docker InfluxDB",
          "groupBy": [
            {
              "params": [
                "$__interval"
              ],
              "type": "time"
            },
            {
              "params": [
                "source"
              ],
              "type": "tag"
            },
            {
              "params": [
                "name"
              ],
              "type": "tag"
            },
            {
              "params": [
                "null"
              ],
              "type": "fill"
            }
          ],
          "measurement": "nokia_port_transceiver",
          "orderByTime": "ASC",
          "policy": "default",
          "refId": "A",
          "resultFormat": "time_series",
          "select": [
            [
              {
                "params": [
                  "digital_diagnostic_monitoring_temperature_current"
                ],
                "type": "field"
              },
              {
                "params": [],
                "type": "mean"
              }
            ]
          ],
          "tags": [
            {
              "key": "source",
              "operator": "=~",
              "value": "/^$HostName$/"
            },
            {
              "condition": "AND",
              "key": "port_id",
              "operator": "=",
              "value": "/^$PortNumber$/"
            }
          ]
        },
        {
          "alias": "Voltage",
          "datasource": "Docker InfluxDB",
          "groupBy": [
            {
              "params": [
                "$__interval"
              ],
              "type": "time"
            },
            {
              "params": [
                "source"
              ],
              "type": "tag"
            },
            {
              "params": [
                "name"
              ],
              "type": "tag"
            },
            {
              "params": [
                "null"
              ],
              "type": "fill"
            }
          ],
          "hide": false,
          "measurement": "nokia_port_transceiver",
          "orderByTime": "ASC",
          "policy": "default",
          "refId": "B",
          "resultFormat": "time_series",
          "select": [
            [
              {
                "params": [
                  "digital_diagnostic_monitoring_supply_voltage_current"
                ],
                "type": "field"
              },
              {
                "params": [],
                "type": "mean"
              }
            ]
          ],
          "tags": [
            {
              "key": "source",
              "operator": "=~",
              "value": "/^$HostName$/"
            },
            {
              "condition": "AND",
              "key": "port_id",
              "operator": "=",
              "value": "/^$PortNumber$/"
            }
          ]
        }
      ],
      "title": "Environmentals",
      "type": "timeseries"
    },
    {
      "datasource": "Docker InfluxDB",
      "description": "",
      "fieldConfig": {
        "defaults": {
          "color": {
            "mode": "palette-classic"
          },
          "mappings": [],
          "thresholds": {
            "mode": "absolute",
            "steps": [
              {
                "color": "green",
                "value": 0
              }
            ]
          },
          "unit": "dB"
        },
        "overrides": []
      },
      "gridPos": {
        "h": 4,
        "w": 4,
        "x": 0,
        "y": 14
      },
      "id": 25,
      "options": {
        "colorMode": "value",
        "graphMode": "area",
        "justifyMode": "auto",
        "orientation": "auto",
        "percentChangeColorMode": "standard",
        "reduceOptions": {
          "calcs": [
            "lastNotNull"
          ],
          "fields": "",
          "values": false
        },
        "showPercentChange": false,
        "text": {},
        "textMode": "auto",
        "wideLayout": true
      },
      "pluginVersion": "12.3.0-18783997389",
      "targets": [
        {
          "alias": "Q Factor",
          "datasource": "Docker InfluxDB",
          "groupBy": [
            {
              "params": [
                "$__interval"
              ],
              "type": "time"
            },
            {
              "params": [
                "source"
              ],
              "type": "tag"
            },
            {
              "params": [
                "name"
              ],
              "type": "tag"
            },
            {
              "params": [
                "null"
              ],
              "type": "fill"
            }
          ],
          "hide": false,
          "measurement": "nokia_port_dwdm",
          "orderByTime": "ASC",
          "policy": "autogen",
          "query": "SELECT mean(\"snr\") FROM \"Cisco-IOS-XR-controller-optics-oper:optics-oper/optics-ports/optics-port/optics-info\" WHERE (\"source\" = '8201') AND $timeFilter GROUP BY time($__interval), \"source\", \"name\" fill(null)",
          "rawQuery": false,
          "refId": "B",
          "resultFormat": "time_series",
          "select": [
            [
              {
                "params": [
                  "coherent_statistics_received_quality_current"
                ],
                "type": "field"
              },
              {
                "params": [],
                "type": "mean"
              },
              {
                "params": [
                  " / 10"
                ],
                "type": "math"
              }
            ]
          ],
          "tags": [
            {
              "key": "source",
              "operator": "=~",
              "value": "/^$HostName$/"
            },
            {
              "condition": "AND",
              "key": "port_id::tag",
              "operator": "=",
              "value": "/^$PortNumber$/"
            }
          ]
        },
        {
          "alias": "Q margin",
          "datasource": "Docker InfluxDB",
          "groupBy": [
            {
              "params": [
                "$__interval"
              ],
              "type": "time"
            },
            {
              "params": [
                "controller_name"
              ],
              "type": "tag"
            },
            {
              "params": [
                "source"
              ],
              "type": "tag"
            },
            {
              "params": [
                "null"
              ],
              "type": "fill"
            }
          ],
          "hide": false,
          "measurement": "nokia_port_dwdm",
          "orderByTime": "ASC",
          "policy": "autogen",
          "refId": "C",
          "resultFormat": "time_series",
          "select": [
            [
              {
                "params": [
                  "coherent_rx_quality_margin"
                ],
                "type": "field"
              },
              {
                "params": [],
                "type": "mean"
              },
              {
                "params": [
                  " / 10"
                ],
                "type": "math"
              }
            ]
          ],
          "tags": [
            {
              "key": "source",
              "operator": "=~",
              "value": "/^$HostName$/"
            },
            {
              "condition": "AND",
              "key": "port_id::tag",
              "operator": "=",
              "value": "/^$PortNumber$/"
            }
          ]
        }
      ],
      "title": "Q margin",
      "type": "stat"
    },
    {
      "datasource": "Docker InfluxDB",
      "description": "",
      "fieldConfig": {
        "defaults": {
          "color": {
            "mode": "palette-classic"
          },
          "mappings": [],
          "thresholds": {
            "mode": "absolute",
            "steps": [
              {
                "color": "green",
                "value": 0
              }
            ]
          },
          "unit": "dB"
        },
        "overrides": []
      },
      "gridPos": {
        "h": 4,
        "w": 4,
        "x": 4,
        "y": 14
      },
      "id": 23,
      "options": {
        "colorMode": "value",
        "graphMode": "area",
        "justifyMode": "auto",
        "orientation": "auto",
        "percentChangeColorMode": "standard",
        "reduceOptions": {
          "calcs": [
            "lastNotNull"
          ],
          "fields": "",
          "values": false
        },
        "showPercentChange": false,
        "text": {},
        "textMode": "auto",
        "wideLayout": true
      },
      "pluginVersion": "12.3.0-18783997389",
      "targets": [
        {
          "alias": "OSNR",
          "datasource": "Docker InfluxDB",
          "groupBy": [
            {
              "params": [
                "$__interval"
              ],
              "type": "time"
            },
            {
              "params": [
                "source"
              ],
              "type": "tag"
            },
            {
              "params": [
                "name"
              ],
              "type": "tag"
            },
            {
              "params": [
                "null"
              ],
              "type": "fill"
            }
          ],
          "measurement": "nokia_port_dwdm",
          "orderByTime": "ASC",
          "policy": "default",
          "refId": "A",
          "resultFormat": "time_series",
          "select": [
            [
              {
                "params": [
                  "coherent_statistics_received_optical_signal_to_noise_ratio_current"
                ],
                "type": "field"
              },
              {
                "params": [],
                "type": "mean"
              },
              {
                "params": [
                  " / 10"
                ],
                "type": "math"
              }
            ]
          ],
          "tags": [
            {
              "key": "source",
              "operator": "=~",
              "value": "/^$HostName$/"
            },
            {
              "condition": "AND",
              "key": "port_id",
              "operator": "=",
              "value": "/^$PortNumber$/"
            }
          ]
        },
        {
          "alias": "OSNR Margin",
          "datasource": "Docker InfluxDB",
          "groupBy": [
            {
              "params": [
                "$__interval"
              ],
              "type": "time"
            },
            {
              "params": [
                "source"
              ],
              "type": "tag"
            },
            {
              "params": [
                "name"
              ],
              "type": "tag"
            },
            {
              "params": [
                "null"
              ],
              "type": "fill"
            }
          ],
          "hide": false,
          "measurement": "nokia_port_dwdm",
          "orderByTime": "ASC",
          "policy": "default",
          "refId": "C",
          "resultFormat": "time_series",
          "select": [
            [
              {
                "params": [
                  "coherent_statistics_received_optical_signal_to_noise_ratio_current"
                ],
                "type": "field"
              },
              {
                "params": [],
                "type": "mean"
              },
              {
                "params": [
                  "/10 - 24"
                ],
                "type": "math"
              }
            ]
          ],
          "tags": [
            {
              "key": "source",
              "operator": "=~",
              "value": "/^$HostName$/"
            },
            {
              "condition": "AND",
              "key": "port_id",
              "operator": "=",
              "value": "/^$PortNumber$/"
            }
          ]
        }
      ],
      "title": "Optical Signal to Noise Ratio",
      "type": "stat"
    },
    {
      "datasource": "Docker InfluxDB",
      "description": "",
      "fieldConfig": {
        "defaults": {
          "color": {
            "mode": "palette-classic"
          },
          "custom": {
            "axisBorderShow": false,
            "axisCenteredZero": false,
            "axisColorMode": "text",
            "axisLabel": "Ratio",
            "axisPlacement": "auto",
            "barAlignment": 0,
            "barWidthFactor": 0.6,
            "drawStyle": "line",
            "fillOpacity": 0,
            "gradientMode": "none",
            "hideFrom": {
              "legend": false,
              "tooltip": false,
              "viz": false
            },
            "insertNulls": false,
            "lineInterpolation": "linear",
            "lineWidth": 1,
            "pointSize": 5,
            "scaleDistribution": {
              "type": "linear"
            },
            "showPoints": "auto",
            "showValues": false,
            "spanNulls": true,
            "stacking": {
              "group": "A",
              "mode": "none"
            },
            "thresholdsStyle": {
              "mode": "off"
            }
          },
          "mappings": [],
          "thresholds": {
            "mode": "absolute",
            "steps": [
              {
                "color": "green",
                "value": 0
              }
            ]
          }
        },
        "overrides": []
      },
      "gridPos": {
        "h": 8,
        "w": 6,
        "x": 14,
        "y": 14
      },
      "id": 14,
      "options": {
        "legend": {
          "calcs": [
            "lastNotNull"
          ],
          "displayMode": "list",
          "placement": "bottom",
          "showLegend": true
        },
        "tooltip": {
          "hideZeros": false,
          "mode": "single",
          "sort": "none"
        }
      },
      "pluginVersion": "12.3.0-18783997389",
      "targets": [
        {
          "alias": "Chromatic Dispertion",
          "datasource": "Docker InfluxDB",
          "groupBy": [
            {
              "params": [
                "$__interval"
              ],
              "type": "time"
            },
            {
              "params": [
                "null"
              ],
              "type": "fill"
            }
          ],
          "hide": false,
          "measurement": "nokia_port_dwdm",
          "orderByTime": "ASC",
          "policy": "default",
          "refId": "A",
          "resultFormat": "time_series",
          "select": [
            [
              {
                "params": [
                  "coherent_statistics_received_chromatic_dispersion_current"
                ],
                "type": "field"
              },
              {
                "params": [],
                "type": "mean"
              }
            ]
          ],
          "tags": [
            {
              "key": "source",
              "operator": "=~",
              "value": "/^$HostName$/"
            },
            {
              "condition": "AND",
              "key": "port_id",
              "operator": "=",
              "value": "$PortNumber"
            }
          ]
        },
        {
          "alias": "Differential Group Delay",
          "datasource": "Docker InfluxDB",
          "groupBy": [
            {
              "params": [
                "$__interval"
              ],
              "type": "time"
            },
            {
              "params": [
                "null"
              ],
              "type": "fill"
            }
          ],
          "hide": false,
          "measurement": "nokia_port_dwdm",
          "orderByTime": "ASC",
          "policy": "default",
          "refId": "B",
          "resultFormat": "time_series",
          "select": [
            [
              {
                "params": [
                  "coherent_statistics_received_differential_group_delay_current"
                ],
                "type": "field"
              },
              {
                "params": [],
                "type": "mean"
              }
            ]
          ],
          "tags": [
            {
              "key": "source",
              "operator": "=~",
              "value": "/^$HostName$/"
            },
            {
              "condition": "AND",
              "key": "port_id",
              "operator": "=",
              "value": "$PortNumber"
            }
          ]
        }
      ],
      "title": "Optical Impairments",
      "type": "timeseries"
    },
    {
      "datasource": "Docker InfluxDB",
      "description": "",
      "fieldConfig": {
        "defaults": {
          "color": {
            "mode": "palette-classic"
          },
          "custom": {
            "axisBorderShow": false,
            "axisCenteredZero": false,
            "axisColorMode": "text",
            "axisLabel": "Ratio",
            "axisPlacement": "auto",
            "barAlignment": 0,
            "barWidthFactor": 0.6,
            "drawStyle": "line",
            "fillOpacity": 0,
            "gradientMode": "none",
            "hideFrom": {
              "legend": false,
              "tooltip": false,
              "viz": false
            },
            "insertNulls": false,
            "lineInterpolation": "linear",
            "lineWidth": 1,
            "pointSize": 5,
            "scaleDistribution": {
              "type": "linear"
            },
            "showPoints": "auto",
            "showValues": false,
            "spanNulls": true,
            "stacking": {
              "group": "A",
              "mode": "none"
            },
            "thresholdsStyle": {
              "mode": "off"
            }
          },
          "mappings": [],
          "thresholds": {
            "mode": "absolute",
            "steps": [
              {
                "color": "green",
                "value": 0
              }
            ]
          }
        },
        "overrides": []
      },
      "gridPos": {
        "h": 6,
        "w": 6,
        "x": 8,
        "y": 16
      },
      "id": 12,
      "options": {
        "legend": {
          "calcs": [
            "lastNotNull"
          ],
          "displayMode": "list",
          "placement": "bottom",
          "showLegend": true
        },
        "tooltip": {
          "hideZeros": false,
          "mode": "single",
          "sort": "none"
        }
      },
      "pluginVersion": "12.3.0-18783997389",
      "targets": [
        {
          "alias": "OSNR",
          "datasource": "Docker InfluxDB",
          "groupBy": [
            {
              "params": [
                "$__interval"
              ],
              "type": "time"
            },
            {
              "params": [
                "source"
              ],
              "type": "tag"
            },
            {
              "params": [
                "name"
              ],
              "type": "tag"
            },
            {
              "params": [
                "null"
              ],
              "type": "fill"
            }
          ],
          "measurement": "nokia_port_dwdm",
          "orderByTime": "ASC",
          "policy": "default",
          "refId": "A",
          "resultFormat": "time_series",
          "select": [
            [
              {
                "params": [
                  "coherent_statistics_received_optical_signal_to_noise_ratio_current"
                ],
                "type": "field"
              },
              {
                "params": [],
                "type": "mean"
              },
              {
                "params": [
                  " / 10"
                ],
                "type": "math"
              }
            ]
          ],
          "tags": [
            {
              "key": "source",
              "operator": "=~",
              "value": "/^$HostName$/"
            },
            {
              "condition": "AND",
              "key": "port_id",
              "operator": "=",
              "value": "/^$PortNumber$/"
            }
          ]
        },
        {
          "alias": "ESNR",
          "datasource": "Docker InfluxDB",
          "groupBy": [
            {
              "params": [
                "$__interval"
              ],
              "type": "time"
            },
            {
              "params": [
                "null"
              ],
              "type": "fill"
            }
          ],
          "hide": false,
          "measurement": "nokia_port_dwdm",
          "orderByTime": "ASC",
          "policy": "default",
          "refId": "B",
          "resultFormat": "time_series",
          "select": [
            [
              {
                "params": [
                  "coherent_statistics_received_electrical_signal_to_noise_ratio_current"
                ],
                "type": "field"
              },
              {
                "params": [],
                "type": "mean"
              },
              {
                "params": [
                  " / 10"
                ],
                "type": "math"
              }
            ]
          ],
          "tags": [
            {
              "key": "source",
              "operator": "=~",
              "value": "/^$HostName$/"
            },
            {
              "condition": "AND",
              "key": "port_id",
              "operator": "=",
              "value": "/^$PortNumber$/"
            }
          ]
        }
      ],
      "title": "Optics Signal to Noise Ratio",
      "type": "timeseries"
    },
    {
      "datasource": "Docker InfluxDB",
      "description": "",
      "fieldConfig": {
        "defaults": {
          "color": {
            "mode": "palette-classic"
          },
          "mappings": [],
          "thresholds": {
            "mode": "absolute",
            "steps": [
              {
                "color": "green",
                "value": 0
              }
            ]
          },
          "unit": "ps/nm"
        },
        "overrides": [
          {
            "matcher": {
              "id": "byName",
              "options": "eSNR"
            },
            "properties": [
              {
                "id": "unit",
                "value": "dB"
              },
              {
                "id": "decimals",
                "value": 1
              }
            ]
          },
          {
            "matcher": {
              "id": "byName",
              "options": "Differential Group Delay"
            },
            "properties": [
              {
                "id": "unit",
                "value": "ps"
              }
            ]
          }
        ]
      },
      "gridPos": {
        "h": 4,
        "w": 8,
        "x": 0,
        "y": 18
      },
      "id": 15,
      "options": {
        "colorMode": "value",
        "graphMode": "area",
        "justifyMode": "auto",
        "orientation": "auto",
        "percentChangeColorMode": "standard",
        "reduceOptions": {
          "calcs": [
            "lastNotNull"
          ],
          "fields": "",
          "values": false
        },
        "showPercentChange": false,
        "text": {},
        "textMode": "auto",
        "wideLayout": true
      },
      "pluginVersion": "12.3.0-18783997389",
      "targets": [
        {
          "alias": "Chromatic Dispersion",
          "datasource": "Docker InfluxDB",
          "groupBy": [
            {
              "params": [
                "$__interval"
              ],
              "type": "time"
            },
            {
              "params": [
                "source"
              ],
              "type": "tag"
            },
            {
              "params": [
                "name"
              ],
              "type": "tag"
            },
            {
              "params": [
                "null"
              ],
              "type": "fill"
            }
          ],
          "measurement": "nokia_port_dwdm",
          "orderByTime": "ASC",
          "policy": "default",
          "refId": "A",
          "resultFormat": "time_series",
          "select": [
            [
              {
                "params": [
                  "coherent_statistics_received_chromatic_dispersion_current"
                ],
                "type": "field"
              },
              {
                "params": [],
                "type": "mean"
              }
            ]
          ],
          "tags": [
            {
              "key": "source",
              "operator": "=~",
              "value": "/^$HostName$/"
            },
            {
              "condition": "AND",
              "key": "port_id",
              "operator": "=",
              "value": "/^$PortNumber$/"
            }
          ]
        },
        {
          "alias": "Differential Group Delay",
          "datasource": "Docker InfluxDB",
          "groupBy": [
            {
              "params": [
                "$__interval"
              ],
              "type": "time"
            },
            {
              "params": [
                "source"
              ],
              "type": "tag"
            },
            {
              "params": [
                "name"
              ],
              "type": "tag"
            },
            {
              "params": [
                "null"
              ],
              "type": "fill"
            }
          ],
          "hide": false,
          "measurement": "nokia_port_dwdm",
          "orderByTime": "ASC",
          "policy": "autogen",
          "query": "SELECT mean(\"snr\") FROM \"Cisco-IOS-XR-controller-optics-oper:optics-oper/optics-ports/optics-port/optics-info\" WHERE (\"source\" = '8201') AND $timeFilter GROUP BY time($__interval), \"source\", \"name\" fill(null)",
          "rawQuery": false,
          "refId": "B",
          "resultFormat": "time_series",
          "select": [
            [
              {
                "params": [
                  "coherent_statistics_received_differential_group_delay_current"
                ],
                "type": "field"
              },
              {
                "params": [],
                "type": "mean"
              }
            ]
          ],
          "tags": [
            {
              "key": "source",
              "operator": "=~",
              "value": "/^$HostName$/"
            },
            {
              "condition": "AND",
              "key": "port_id",
              "operator": "=",
              "value": "/^$PortNumber$/"
            }
          ]
        },
        {
          "alias": "ESNR",
          "datasource": "Docker InfluxDB",
          "groupBy": [
            {
              "params": [
                "$__interval"
              ],
              "type": "time"
            },
            {
              "params": [
                "controller_name"
              ],
              "type": "tag"
            },
            {
              "params": [
                "source"
              ],
              "type": "tag"
            },
            {
              "params": [
                "null"
              ],
              "type": "fill"
            }
          ],
          "hide": false,
          "measurement": "nokia_port_dwdm",
          "orderByTime": "ASC",
          "policy": "autogen",
          "refId": "C",
          "resultFormat": "time_series",
          "select": [
            [
              {
                "params": [
                  "coherent_statistics_received_electrical_signal_to_noise_ratio_current"
                ],
                "type": "field"
              },
              {
                "params": [],
                "type": "mean"
              },
              {
                "params": [
                  " / 10"
                ],
                "type": "math"
              }
            ]
          ],
          "tags": [
            {
              "key": "source",
              "operator": "=~",
              "value": "/^$HostName$/"
            },
            {
              "condition": "AND",
              "key": "port_id",
              "operator": "=",
              "value": "/^$PortNumber$/"
            }
          ]
        }
      ],
      "title": "Optical Impairments",
      "type": "stat"
    }
  ],
  "preload": false,
  "refresh": "",
  "schemaVersion": 42,
  "tags": [],
  "templating": {
    "list": [
      {
        "current": {
          "text": "1/1/c28",
          "value": "1/1/c28"
        },
        "hide": 2,
        "name": "PortNumber",
        "query": "1/1/c28",
        "skipUrlSync": true,
        "type": "constant"
      },
      {
        "current": {
          "text": "1/1/c28/1",
          "value": "1/1/c28/1"
        },
        "hide": 2,
        "name": "EthPortNumber",
        "query": "1/1/c28/1",
        "skipUrlSync": true,
        "type": "constant"
      },
      {
        "current": {
          "text": "172.30.150.150",
          "value": "172.30.150.150"
        },
        "hide": 2,
        "name": "HostName",
        "query": "172.30.150.150",
        "skipUrlSync": true,
        "type": "constant"
      }
    ]
  },
  "time": {
    "from": "now-30m",
    "to": "now"
  },
  "timepicker": {},
  "timezone": "",
  "title": "OpenZR+ Nokia port 1/1/c28 - Circuit ID 2000",
  "uid": "Q4aR2BOnz",
  "version": 1
}